tostorchconnector/__init__.py
tostorchconnector/run_execption.py
tostorchconnector/tos_checkpoint.py
tostorchconnector/tos_client.py
tostorchconnector/tos_common.py
tostorchconnector/tos_distributed_checkpoint.py
tostorchconnector/tos_iterable_dataset.py
tostorchconnector/tos_map_dataset.py
tostorchconnector/tos_object_meta.py
tostorchconnector/tos_object_reader.py
tostorchconnector/tos_object_writer.py
tostorchconnector/toscloud_stream.py
tostorchconnector-1.1.11.dist-info/licenses/LICENSE
tostorchconnector-1.1.11.dist-info/METADATA
tostorchconnector-1.1.11.dist-info/WHEEL
tostorchconnector-1.1.11.dist-info/top_level.txt
tostorchconnector-1.1.11.dist-info/RECORD
