Metadata-Version: 2.4
Name: tostorchconnector
Version: 1.1.11
Summary: TOS connector integration for PyTorch
Author-email: xiangshijian <xiangshijian@bytedance.com>
Classifier: Development Status :: 4 - Beta
Classifier: Programming Language :: Python :: 3
Classifier: Programming Language :: Python :: 3.8
Classifier: Programming Language :: Python :: 3.9
Classifier: Programming Language :: Python :: 3.10
Classifier: Programming Language :: Python :: 3.11
Classifier: Programming Language :: Python :: 3.12
Classifier: Programming Language :: Python :: 3.13
Classifier: License :: OSI Approved :: Apache Software License
Classifier: Operating System :: OS Independent
Classifier: Topic :: Utilities
Requires-Python: <3.14,>=3.8
License-File: LICENSE
Requires-Dist: torch>=2.0
Requires-Dist: tos>=2.8.0
Requires-Dist: tosnativeclient>=1.1.10
Dynamic: license-file
